<?xml version="1.0"?>
<monster name="Dwarf" nameDescription="a dwarf" speed="170" experience="45" race="blood">
  <health now="90" max="90" />
  <look typeex="0" type="69" head="0" body="0" legs="0" feet="0" corpse="6007" />
  <voices interval="5000" chance="10">
    <voice sentence="Hail Durin!" />
  </voices>
  <elements>
    <element earthPercent="70" />
    <element firePercent="-5" />
    <element deathPercent="-3" />
  </elements>
  <flags>
    <flag summonable="1" />
    <flag attackable="1" />
    <flag hostile="1" />
    <flag illusionable="1" />
    <flag convinceable="1" />
    <flag pushable="1" />
    <flag canpushitems="0" />
    <flag canpushcreatures="0" />
    <flag targetdistance="1" />
    <flag runonhealth="0" />
  </flags>
  <defenses defense="0" armor="8" />
  <attacks>
    <attack name="melee" interval="2000" chance="100" min="0" max="31" />
  </attacks>
</monster>