<?xml version="1.0" encoding="utf-8"?>
<monster name="The Obliverator" nameDescription="The Obliverator" race="fire" speed="280" experience="6000" manacost="0">
  <health now="9020" max="9020" />
  <look typeex="0" type="35" head="0" body="0" legs="0" feet="0" corpse="5995" />
  <flags>
    <flag summonable="0" />
    <flag attackable="1" />
    <flag hostile="1" />
    <flag illusionable="0" />
    <flag convinceable="0" />
    <flag pushable="0" />
    <flag canpushitems="1" />
    <flag canpushcreatures="0" />
    <flag targetdistance="1" />
    <flag runonhealth="0" />
  </flags>
  <immunities>
    <immunity paralyze="0" />
    <immunity invisible="1" />
  </immunities>
  <elements>
    <element physicalPercent="0" />
    <element earthpercent="0" />
    <element firePercent="100" />
    <element energyPercent="50" />
    <element icePercent="0" />
    <element deathPercent="100" />
    <element holyPercent="-1" />
    <element drownPercent="0" />
    <element manaDrainPercent="100" />
    <element lifeDrainPercent="0" />
  </elements>
  <voices interval="5000" chance="10">
    <voice yell="1" sentence="NO ONE WILL BEAT ME!" />
  </voices>
  <defenses mitigation="0" defense="0" armor="0" />
  <changetargetstrategy interval="5000" chance="10" />
  <targetstrategy nearest="0" weakest="0" mostdamage="0" random="100" />
  <attacks />
  <loot />
</monster>